probability_calculator/__init__.py
probability_calculator/part.py
probability_calculator/random_variables.py
probability_calculator-0.3.0.dist-info/METADATA
probability_calculator-0.3.0.dist-info/WHEEL
probability_calculator-0.3.0.dist-info/licenses/LICENSE
probability_calculator-0.3.0.dist-info/RECORD
