Metadata-Version: 2.1
Name: probability_calculator
Version: 0.3.0
Summary: Calculate with and analyze probability densities.
Project-URL: Homepage, https://github.com/HendrikRoehm/probability_calculator
Author-email: Hendrik Roehm <git@roehm.ws>
License-File: LICENSE
Classifier: Development Status :: 3 - Alpha
Classifier: Intended Audience :: Science/Research
Classifier: License :: OSI Approved :: Apache Software License
Classifier: Operating System :: OS Independent
Classifier: Programming Language :: Python :: 3
Classifier: Topic :: Scientific/Engineering :: Mathematics
Requires-Python: >=3.7
Requires-Dist: autopep8
Requires-Dist: matplotlib
Requires-Dist: scipy
